Mensajes_eduparra09-6.0.data/scripts/test_1.py
test/__init__.py
test/test_hola.py
Mensajes_eduparra09-6.0.dist-info/LICENSE
Mensajes_eduparra09-6.0.dist-info/METADATA
Mensajes_eduparra09-6.0.dist-info/WHEEL
Mensajes_eduparra09-6.0.dist-info/top_level.txt
Mensajes_eduparra09-6.0.dist-info/RECORD
